kvm48/__init__.py
kvm48/__main__.py
kvm48/aria2.py
kvm48/caterpillar.py
kvm48/config.py
kvm48/dirs.py
kvm48/edit.py
kvm48/koudai.py
kvm48/kvm48.py
kvm48/lock.py
kvm48/peek.py
kvm48/persistence.py
kvm48/update.py
kvm48/utils.py
kvm48/version.py
KVM48-1.3.600.dist-info/COPYING
KVM48-1.3.600.dist-info/METADATA
KVM48-1.3.600.dist-info/WHEEL
KVM48-1.3.600.dist-info/entry_points.txt
KVM48-1.3.600.dist-info/top_level.txt
KVM48-1.3.600.dist-info/RECORD
