Metadata-Version: 2.1
Name: KVM48
Version: 1.3.600
Summary: Koudai48 VOD Manager
Home-page: https://github.com/SNH48Live/KVM48
Author: Zhiming Wang
Author-email: pypi@snh48live.org
License: MIT
Keywords: 48 snh48 koudai48 pocket48
Platform: UNKNOWN
Classifier: Development Status :: 4 - Beta
Classifier: Intended Audience :: End Users/Desktop
Classifier: License :: OSI Approved :: MIT License
Classifier: Programming Language :: Python :: 3
Classifier: Programming Language :: Python :: 3.6
Classifier: Programming Language :: Python :: 3.7
Classifier: Programming Language :: Python :: 3 :: Only
Classifier: Topic :: Multimedia :: Sound/Audio
Classifier: Topic :: Multimedia :: Video
Requires-Dist: PyYAML
Requires-Dist: arrow
Requires-Dist: attrdict
Requires-Dist: caterpillar-hls
Requires-Dist: distlib
Requires-Dist: psutil
Requires-Dist: requests
Requires-Dist: xdgappdirs
